{
  "id": 1079,
  "name": "FC Union Berlin",
  "slug": "union-berlin",
  "players": [
    {
      "id": 83795,
      "display_name": "Frederik Rönnow",
      "image_path": "https://cdn.sportmonks.com/images/soccer/players/19/83795.png",
      "age": 33,
      "height": 188,
      "weight": 77,
      "nationality": "Denmark",
      "position": "GK",
      "position_id": 24,
      "jersey_number": 1,
      "slug": "frederik-rönnow"
    },
    {
      "id": 37543370,
      "display_name": "Yannic Stein",
      "image_path": "https://cdn.sportmonks.com/images/soccer/players/10/37543370.png",
      "age": 20,
      "height": 191,
      "weight": null,
      "nationality": "Germany",
      "position": "GK",
      "position_id": 24,
      "jersey_number": 12,
      "slug": "yannic-stein"
    },
    {
      "id": 37807,
      "display_name": "Carl Klaus",
      "image_path": "https://cdn.sportmonks.com/images/soccer/players/15/37807.png",
      "age": 31,
      "height": 189,
      "weight": 82,
      "nationality": "Germany",
      "position": "GK",
      "position_id": 24,
      "jersey_number": 25,
      "slug": "carl-klaus"
    },
    {
      "id": 47555,
      "display_name": "Matheo Raab",
      "image_path": "https://cdn.sportmonks.com/images/soccer/players/3/47555.png",
      "age": 26,
      "height": 186,
      "weight": null,
      "nationality": "Germany",
      "position": "GK",
      "position_id": 24,
      "jersey_number": 31,
      "slug": "matheo-raab"
    },
    {
      "id": 37650987,
      "display_name": "Andrik Markgraf",
      "image_path": "https://cdn.sportmonks.com/images/soccer/players/11/37650987.png",
      "age": 19,
      "height": 172,
      "weight": null,
      "nationality": "Germany",
      "position": "DF",
      "position_id": 25,
      "jersey_number": 3,
      "slug": "andrik-markgraf"
    },
    {
      "id": 540203,
      "display_name": "Diogo Leite",
      "image_path": "https://cdn.sportmonks.com/images/soccer/players/11/540203.png",
      "age": 26,
      "height": 190,
      "weight": 81,
      "nationality": "Portugal",
      "position": "DF",
      "position_id": 25,
      "jersey_number": 4,
      "slug": "diogo-leite"
    },
    {
      "id": 26860,
      "display_name": "Danilho Doekhi",
      "image_path": "https://cdn.sportmonks.com/images/soccer/players/12/26860.png",
      "age": 27,
      "height": 190,
      "weight": 83,
      "nationality": "Netherlands",
      "position": "DF",
      "position_id": 25,
      "jersey_number": 5,
      "slug": "danilho-doekhi"
    },
    {
      "id": 37536352,
      "display_name": "Leopold Querfeld",
      "image_path": "https://cdn.sportmonks.com/images/soccer/players/0/37536352.png",
      "age": 21,
      "height": 190,
      "weight": null,
      "nationality": "Austria",
      "position": "DF",
      "position_id": 25,
      "jersey_number": 14,
      "slug": "leopold-querfeld"
    },
    {
      "id": 74000,
      "display_name": "Josip Juranovic",
      "image_path": "https://cdn.sportmonks.com/images/soccer/players/16/74000.png",
      "age": 30,
      "height": 173,
      "weight": 69,
      "nationality": "Croatia",
      "position": "DF",
      "position_id": 25,
      "jersey_number": 18,
      "slug": "josip-juranovic"
    },
    {
      "id": 34668,
      "display_name": "Christopher Trimmel",
      "image_path": "https://cdn.sportmonks.com/images/soccer/players/12/34668.png",
      "age": 38,
      "height": 189,
      "weight": 80,
      "nationality": "Austria",
      "position": "DF",
      "position_id": 25,
      "jersey_number": 28,
      "slug": "christopher-trimmel"
    },
    {
      "id": 540548,
      "display_name": "Stanley Nsoki",
      "image_path": "https://cdn.sportmonks.com/images/soccer/players/4/540548.png",
      "age": 26,
      "height": 184,
      "weight": null,
      "nationality": "France",
      "position": "DF",
      "position_id": 25,
      "jersey_number": 34,
      "slug": "stanley-nsoki"
    },
    {
      "id": 1525233,
      "display_name": "Derrick Köhn",
      "image_path": "https://cdn.sportmonks.com/images/soccer/players/17/1525233.png",
      "age": 26,
      "height": 180,
      "weight": null,
      "nationality": "Germany",
      "position": "DF",
      "position_id": 25,
      "jersey_number": 39,
      "slug": "derrick-köhn"
    },
    {
      "id": 37650842,
      "display_name": "Oluwaseun Ogbemudia",
      "image_path": "https://cdn.sportmonks.com/images/soccer/players/26/37650842.png",
      "age": 19,
      "height": 188,
      "weight": null,
      "nationality": "Germany",
      "position": "DF",
      "position_id": 25,
      "jersey_number": 41,
      "slug": "oluwaseun-ogbemudia"
    },
    {
      "id": 37581984,
      "display_name": "Aljoscha Kemlein",
      "image_path": "https://cdn.sportmonks.com/images/soccer/players/0/37581984.png",
      "age": 21,
      "height": 187,
      "weight": null,
      "nationality": "Germany",
      "position": "MF",
      "position_id": 26,
      "jersey_number": 6,
      "slug": "aljoscha-kemlein"
    },
    {
      "id": 31907,
      "display_name": "Rani Khedira",
      "image_path": "https://cdn.sportmonks.com/images/soccer/players/3/31907.png",
      "age": 31,
      "height": 189,
      "weight": 84,
      "nationality": "Germany",
      "position": "MF",
      "position_id": 26,
      "jersey_number": 8,
      "slug": "rani-khedira"
    },
    {
      "id": 11353231,
      "display_name": "Woo-yeong Jeong",
      "image_path": "https://cdn.sportmonks.com/images/soccer/players/15/11353231.png",
      "age": 25,
      "height": 179,
      "weight": 72,
      "nationality": "South Korea",
      "position": "MF",
      "position_id": 26,
      "jersey_number": 11,
      "slug": "woo-yeong-jeong"
    },
    {
      "id": 115485,
      "display_name": "András Schäfer",
      "image_path": "https://cdn.sportmonks.com/images/soccer/players/29/115485.png",
      "age": 26,
      "height": 178,
      "weight": null,
      "nationality": "Hungary",
      "position": "MF",
      "position_id": 26,
      "jersey_number": 13,
      "slug": "andrás-schäfer"
    },
    {
      "id": 37558983,
      "display_name": "Tom Rothe",
      "image_path": "https://cdn.sportmonks.com/images/soccer/players/7/37558983.png",
      "age": 20,
      "height": 193,
      "weight": null,
      "nationality": "Germany",
      "position": "MF",
      "position_id": 26,
      "jersey_number": 15,
      "slug": "tom-rothe"
    },
    {
      "id": 32568,
      "display_name": "Janik Haberer",
      "image_path": "https://cdn.sportmonks.com/images/soccer/players/24/32568.png",
      "age": 31,
      "height": 187,
      "weight": 77,
      "nationality": "Germany",
      "position": "MF",
      "position_id": 26,
      "jersey_number": 19,
      "slug": "janik-haberer"
    },
    {
      "id": 84342,
      "display_name": "Robert Skov",
      "image_path": "https://cdn.sportmonks.com/images/soccer/players/22/84342.png",
      "age": 29,
      "height": 185,
      "weight": 76,
      "nationality": "Denmark",
      "position": "MF",
      "position_id": 26,
      "jersey_number": 24,
      "slug": "robert-skov"
    },
    {
      "id": 96886,
      "display_name": "Lucas Tousart",
      "image_path": "https://cdn.sportmonks.com/images/soccer/players/22/96886.png",
      "age": 28,
      "height": 184,
      "weight": 83,
      "nationality": "France",
      "position": "MF",
      "position_id": 26,
      "jersey_number": 29,
      "slug": "lucas-tousart"
    },
    {
      "id": 82032,
      "display_name": "Alex Král",
      "image_path": "https://cdn.sportmonks.com/images/soccer/players/16/82032.png",
      "age": 27,
      "height": 186,
      "weight": 72,
      "nationality": "Czech Republic",
      "position": "MF",
      "position_id": 26,
      "jersey_number": 33,
      "slug": "alex-král"
    },
    {
      "id": 6286,
      "display_name": "Oliver Burke",
      "image_path": "https://cdn.sportmonks.com/images/soccer/players/14/6286.png",
      "age": 28,
      "height": 188,
      "weight": 74,
      "nationality": "Scotland",
      "position": "FW",
      "position_id": 27,
      "jersey_number": 7,
      "slug": "oliver-burke"
    },
    {
      "id": 37706595,
      "display_name": "Livan Burcu",
      "image_path": "https://cdn.sportmonks.com/images/soccer/players/3/37706595.png",
      "age": 20,
      "height": 180,
      "weight": null,
      "nationality": "Germany",
      "position": "FW",
      "position_id": 27,
      "jersey_number": 9,
      "slug": "livan-burcu"
    },
    {
      "id": 37645082,
      "display_name": "Ilyas Ansah",
      "image_path": "https://cdn.sportmonks.com/images/soccer/players/26/37645082.png",
      "age": 20,
      "height": 197,
      "weight": null,
      "nationality": "Germany",
      "position": "FW",
      "position_id": 27,
      "jersey_number": 10,
      "slug": "ilyas-ansah"
    },
    {
      "id": 37581986,
      "display_name": "David Preu",
      "image_path": "https://cdn.sportmonks.com/images/soccer/players/2/37581986.png",
      "age": 20,
      "height": 172,
      "weight": null,
      "nationality": "Germany",
      "position": "FW",
      "position_id": 27,
      "jersey_number": 17,
      "slug": "david-preu"
    },
    {
      "id": 35117,
      "display_name": "Tim Skarke",
      "image_path": "https://cdn.sportmonks.com/images/soccer/players/13/35117.png",
      "age": 28,
      "height": 181,
      "weight": 70,
      "nationality": "Germany",
      "position": "FW",
      "position_id": 27,
      "jersey_number": 21,
      "slug": "tim-skarke"
    },
    {
      "id": 24838013,
      "display_name": "Andrej Ilic",
      "image_path": "https://cdn.sportmonks.com/images/soccer/players/29/24838013.png",
      "age": 25,
      "height": 189,
      "weight": null,
      "nationality": "Serbia",
      "position": "FW",
      "position_id": 27,
      "jersey_number": 23,
      "slug": "andrej-ilic"
    },
    {
      "id": 37548316,
      "display_name": "Marin Ljubicic",
      "image_path": "https://cdn.sportmonks.com/images/soccer/players/28/37548316.png",
      "age": 23,
      "height": 183,
      "weight": null,
      "nationality": "Croatia",
      "position": "FW",
      "position_id": 27,
      "jersey_number": 27,
      "slug": "marin-ljubicic"
    },
    {
      "id": 37652816,
      "display_name": "Dmytro Bogdanov",
      "image_path": "https://cdn.sportmonks.com/images/soccer/placeholder.png",
      "age": 18,
      "height": 188,
      "weight": null,
      "nationality": "Ukraine",
      "position": "FW",
      "position_id": 27,
      "jersey_number": 30,
      "slug": "dmytro-bogdanov"
    }
  ]
}