{
  "id": 19,
  "name": "Arsenal",
  "slug": "arsenal",
  "players": [
    {
      "id": 3130,
      "display_name": "David Raya",
      "image_path": "https://cdn.sportmonks.com/images/soccer/players/26/3130.png",
      "age": 29,
      "height": 183,
      "weight": 80,
      "nationality": "Spain",
      "position": "GK",
      "position_id": 24,
      "jersey_number": 1,
      "slug": "david-raya"
    },
    {
      "id": 186606,
      "display_name": "Kepa Arrizabalaga",
      "image_path": "https://cdn.sportmonks.com/images/soccer/players/14/186606.png",
      "age": 30,
      "height": 188,
      "weight": 84,
      "nationality": "Spain",
      "position": "GK",
      "position_id": 24,
      "jersey_number": 13,
      "slug": "kepa-arrizabalaga"
    },
    {
      "id": 17544737,
      "display_name": "William Saliba",
      "image_path": "https://cdn.sportmonks.com/images/soccer/players/1/17544737.png",
      "age": 24,
      "height": 192,
      "weight": null,
      "nationality": "France",
      "position": "DF",
      "position_id": 25,
      "jersey_number": 2,
      "slug": "william-saliba"
    },
    {
      "id": 37592228,
      "display_name": "Cristhian Mosquera",
      "image_path": "https://cdn.sportmonks.com/images/soccer/players/4/37592228.png",
      "age": 21,
      "height": 191,
      "weight": null,
      "nationality": "Spain",
      "position": "DF",
      "position_id": 25,
      "jersey_number": 3,
      "slug": "cristhian-mosquera"
    },
    {
      "id": 3259,
      "display_name": "Ben White",
      "image_path": "https://cdn.sportmonks.com/images/soccer/players/27/3259.png",
      "age": 27,
      "height": 186,
      "weight": 78,
      "nationality": "England",
      "position": "DF",
      "position_id": 25,
      "jersey_number": 4,
      "slug": "ben-white"
    },
    {
      "id": 97811,
      "display_name": "Gabriel Magalhães",
      "image_path": "https://cdn.sportmonks.com/images/soccer/players/19/97811.png",
      "age": 27,
      "height": 190,
      "weight": 78,
      "nationality": "Brazil",
      "position": "DF",
      "position_id": 25,
      "jersey_number": 6,
      "slug": "gabriel-magalhães"
    },
    {
      "id": 5270466,
      "display_name": "Jurrien Timber",
      "image_path": "https://cdn.sportmonks.com/images/soccer/players/2/5270466.png",
      "age": 24,
      "height": 179,
      "weight": null,
      "nationality": "Netherlands",
      "position": "DF",
      "position_id": 25,
      "jersey_number": 12,
      "slug": "jurrien-timber"
    },
    {
      "id": 8403613,
      "display_name": "Jakub Kiwior",
      "image_path": "https://cdn.sportmonks.com/images/soccer/players/29/8403613.png",
      "age": 25,
      "height": 189,
      "weight": null,
      "nationality": "Poland",
      "position": "DF",
      "position_id": 25,
      "jersey_number": 15,
      "slug": "jakub-kiwior"
    },
    {
      "id": 26603,
      "display_name": "Oleksandr Zinchenko",
      "image_path": "https://cdn.sportmonks.com/images/soccer/players/11/26603.png",
      "age": 28,
      "height": 175,
      "weight": 64,
      "nationality": "Ukraine",
      "position": "DF",
      "position_id": 25,
      "jersey_number": 17,
      "slug": "oleksandr-zinchenko"
    },
    {
      "id": 23278684,
      "display_name": "Riccardo Calafiori ",
      "image_path": "https://cdn.sportmonks.com/images/soccer/players/28/23278684.png",
      "age": 23,
      "height": 188,
      "weight": null,
      "nationality": "Italy",
      "position": "DF",
      "position_id": 25,
      "jersey_number": 33,
      "slug": "riccardo-calafiori "
    },
    {
      "id": 37568815,
      "display_name": "Myles Lewis-Skelly",
      "image_path": "https://cdn.sportmonks.com/images/soccer/players/15/37568815.png",
      "age": 18,
      "height": 178,
      "weight": null,
      "nationality": "England",
      "position": "DF",
      "position_id": 25,
      "jersey_number": 49,
      "slug": "myles-lewis-skelly"
    },
    {
      "id": 26823,
      "display_name": "Martin Ødegaard ",
      "image_path": "https://cdn.sportmonks.com/images/soccer/players/7/26823.png",
      "age": 26,
      "height": 178,
      "weight": 68,
      "nationality": "Norway",
      "position": "MF",
      "position_id": 26,
      "jersey_number": 8,
      "slug": "martin-ødegaard "
    },
    {
      "id": 7643,
      "display_name": "Eberechi Eze",
      "image_path": "https://cdn.sportmonks.com/images/soccer/players/27/7643.png",
      "age": 27,
      "height": 178,
      "weight": null,
      "nationality": "England",
      "position": "MF",
      "position_id": 26,
      "jersey_number": 10,
      "slug": "eberechi-eze"
    },
    {
      "id": 31609,
      "display_name": "Christian Nørgaard",
      "image_path": "https://cdn.sportmonks.com/images/soccer/players/25/31609.png",
      "age": 31,
      "height": 187,
      "weight": 76,
      "nationality": "Denmark",
      "position": "MF",
      "position_id": 26,
      "jersey_number": 16,
      "slug": "christian-nørgaard"
    },
    {
      "id": 5270497,
      "display_name": "Fábio Vieira",
      "image_path": "https://cdn.sportmonks.com/images/soccer/players/1/5270497.png",
      "age": 25,
      "height": 170,
      "weight": null,
      "nationality": "Portugal",
      "position": "MF",
      "position_id": 26,
      "jersey_number": 21,
      "slug": "fábio-vieira"
    },
    {
      "id": 37568808,
      "display_name": "Ethan Nwaneri",
      "image_path": "https://cdn.sportmonks.com/images/soccer/players/8/37568808.png",
      "age": 18,
      "height": 176,
      "weight": null,
      "nationality": "England",
      "position": "MF",
      "position_id": 26,
      "jersey_number": 22,
      "slug": "ethan-nwaneri"
    },
    {
      "id": 32710,
      "display_name": "Mikel Merino",
      "image_path": "https://cdn.sportmonks.com/images/soccer/players/6/32710.png",
      "age": 29,
      "height": 189,
      "weight": 83,
      "nationality": "Spain",
      "position": "MF",
      "position_id": 26,
      "jersey_number": 23,
      "slug": "mikel-merino"
    },
    {
      "id": 538907,
      "display_name": "Albert Sambi Lokonga",
      "image_path": "https://cdn.sportmonks.com/images/soccer/players/27/538907.png",
      "age": 25,
      "height": 183,
      "weight": 67,
      "nationality": "Belgium",
      "position": "MF",
      "position_id": 26,
      "jersey_number": 28,
      "slug": "albert-sambi-lokonga"
    },
    {
      "id": 530762,
      "display_name": "Martín Zubimendi",
      "image_path": "https://cdn.sportmonks.com/images/soccer/players/10/530762.png",
      "age": 26,
      "height": 181,
      "weight": 74,
      "nationality": "Spain",
      "position": "MF",
      "position_id": 26,
      "jersey_number": 36,
      "slug": "martín-zubimendi"
    },
    {
      "id": 5273,
      "display_name": "Declan Rice",
      "image_path": "https://cdn.sportmonks.com/images/soccer/players/25/5273.png",
      "age": 26,
      "height": 188,
      "weight": 76,
      "nationality": "England",
      "position": "MF",
      "position_id": 26,
      "jersey_number": 41,
      "slug": "declan-rice"
    },
    {
      "id": 37720618,
      "display_name": "M. Dowman",
      "image_path": "https://cdn.sportmonks.com/images/soccer/placeholder.png",
      "age": 15,
      "height": null,
      "weight": null,
      "nationality": "England",
      "position": "MF",
      "position_id": 26,
      "jersey_number": 56,
      "slug": "m-dowman"
    },
    {
      "id": 16827155,
      "display_name": "Bukayo Saka",
      "image_path": "https://cdn.sportmonks.com/images/soccer/players/19/16827155.png",
      "age": 23,
      "height": 178,
      "weight": 72,
      "nationality": "England",
      "position": "FW",
      "position_id": 27,
      "jersey_number": 7,
      "slug": "bukayo-saka"
    },
    {
      "id": 5329,
      "display_name": "Gabriel Jesus ",
      "image_path": "https://cdn.sportmonks.com/images/soccer/players/17/5329.png",
      "age": 28,
      "height": 175,
      "weight": 73,
      "nationality": "Brazil",
      "position": "FW",
      "position_id": 27,
      "jersey_number": 9,
      "slug": "gabriel-jesus "
    },
    {
      "id": 10959356,
      "display_name": "Gabriel Martinelli",
      "image_path": "https://cdn.sportmonks.com/images/soccer/players/28/10959356.png",
      "age": 24,
      "height": 178,
      "weight": null,
      "nationality": "Brazil",
      "position": "FW",
      "position_id": 27,
      "jersey_number": 11,
      "slug": "gabriel-martinelli"
    },
    {
      "id": 194167,
      "display_name": "Viktor Gyökeres",
      "image_path": "https://cdn.sportmonks.com/images/soccer/players/23/194167.png",
      "age": 27,
      "height": 187,
      "weight": 86,
      "nationality": "Sweden",
      "position": "FW",
      "position_id": 27,
      "jersey_number": 14,
      "slug": "viktor-gyökeres"
    },
    {
      "id": 61780,
      "display_name": "Leandro Trossard",
      "image_path": "https://cdn.sportmonks.com/images/soccer/players/20/61780.png",
      "age": 30,
      "height": 172,
      "weight": 61,
      "nationality": "Belgium",
      "position": "FW",
      "position_id": 27,
      "jersey_number": 19,
      "slug": "leandro-trossard"
    },
    {
      "id": 25217662,
      "display_name": "Noni Madueke",
      "image_path": "https://cdn.sportmonks.com/images/soccer/players/30/25217662.png",
      "age": 23,
      "height": 182,
      "weight": null,
      "nationality": "England",
      "position": "FW",
      "position_id": 27,
      "jersey_number": 20,
      "slug": "noni-madueke"
    },
    {
      "id": 537759,
      "display_name": "Reiss Nelson",
      "image_path": "https://cdn.sportmonks.com/images/soccer/players/31/537759.png",
      "age": 25,
      "height": 175,
      "weight": 71,
      "nationality": "England",
      "position": "FW",
      "position_id": 27,
      "jersey_number": 24,
      "slug": "reiss-nelson"
    },
    {
      "id": 32612,
      "display_name": "Kai Havertz",
      "image_path": "https://cdn.sportmonks.com/images/soccer/players/4/32612.png",
      "age": 26,
      "height": 193,
      "weight": 83,
      "nationality": "Germany",
      "position": "FW",
      "position_id": 27,
      "jersey_number": 29,
      "slug": "kai-havertz"
    }
  ]
}