{
  "id": 353,
  "name": "St. Pauli",
  "slug": "st-pauli",
  "players": [
    {
      "id": 27066520,
      "display_name": "Ben Voll",
      "image_path": "https://cdn.sportmonks.com/images/soccer/players/24/27066520.png",
      "age": 24,
      "height": 195,
      "weight": null,
      "nationality": "Germany",
      "position": "GK",
      "position_id": 24,
      "jersey_number": 1,
      "slug": "ben-voll"
    },
    {
      "id": 68208,
      "display_name": "Nikola Vasilj",
      "image_path": "https://cdn.sportmonks.com/images/soccer/players/16/68208.png",
      "age": 29,
      "height": 193,
      "weight": 85,
      "nationality": "Bosnia and Herzegovina",
      "position": "GK",
      "position_id": 24,
      "jersey_number": 22,
      "slug": "nikola-vasilj"
    },
    {
      "id": 24816914,
      "display_name": "Simon Spari",
      "image_path": "https://cdn.sportmonks.com/images/soccer/players/18/24816914.png",
      "age": 23,
      "height": 196,
      "weight": null,
      "nationality": "Austria",
      "position": "GK",
      "position_id": 24,
      "jersey_number": 30,
      "slug": "simon-spari"
    },
    {
      "id": 78320,
      "display_name": "Manolis Saliakas",
      "image_path": "https://cdn.sportmonks.com/images/soccer/players/16/78320.png",
      "age": 28,
      "height": 177,
      "weight": 74,
      "nationality": "Greece",
      "position": "DF",
      "position_id": 25,
      "jersey_number": 2,
      "slug": "manolis-saliakas"
    },
    {
      "id": 88119,
      "display_name": "Karol Mets",
      "image_path": "https://cdn.sportmonks.com/images/soccer/players/23/88119.png",
      "age": 32,
      "height": 191,
      "weight": 91,
      "nationality": "Estonia",
      "position": "DF",
      "position_id": 25,
      "jersey_number": 3,
      "slug": "karol-mets"
    },
    {
      "id": 21036726,
      "display_name": "David Nemeth",
      "image_path": "https://cdn.sportmonks.com/images/soccer/players/22/21036726.png",
      "age": 24,
      "height": 191,
      "weight": null,
      "nationality": "Austria",
      "position": "DF",
      "position_id": 25,
      "jersey_number": 4,
      "slug": "david-nemeth"
    },
    {
      "id": 32516,
      "display_name": "Hauke Wahl",
      "image_path": "https://cdn.sportmonks.com/images/soccer/players/4/32516.png",
      "age": 31,
      "height": 189,
      "weight": 85,
      "nationality": "Germany",
      "position": "DF",
      "position_id": 25,
      "jersey_number": 5,
      "slug": "hauke-wahl"
    },
    {
      "id": 190972,
      "display_name": "Eric Smith",
      "image_path": "https://cdn.sportmonks.com/images/soccer/players/28/190972.png",
      "age": 28,
      "height": 192,
      "weight": 86,
      "nationality": "Sweden",
      "position": "DF",
      "position_id": 25,
      "jersey_number": 8,
      "slug": "eric-smith"
    },
    {
      "id": 20347176,
      "display_name": "Arkadiusz Pyrka",
      "image_path": "https://cdn.sportmonks.com/images/soccer/players/8/20347176.png",
      "age": 22,
      "height": 177,
      "weight": null,
      "nationality": "Poland",
      "position": "DF",
      "position_id": 25,
      "jersey_number": 11,
      "slug": "arkadiusz-pyrka"
    },
    {
      "id": 37536520,
      "display_name": "Fin Stevens",
      "image_path": "https://cdn.sportmonks.com/images/soccer/players/8/37536520.png",
      "age": 22,
      "height": 179,
      "weight": null,
      "nationality": "Wales",
      "position": "DF",
      "position_id": 25,
      "jersey_number": 14,
      "slug": "fin-stevens"
    },
    {
      "id": 36547,
      "display_name": "Lars Ritzka",
      "image_path": "https://cdn.sportmonks.com/images/soccer/players/3/36547.png",
      "age": 27,
      "height": 185,
      "weight": 78,
      "nationality": "Germany",
      "position": "DF",
      "position_id": 25,
      "jersey_number": 21,
      "slug": "lars-ritzka"
    },
    {
      "id": 37266285,
      "display_name": "Louis Oppie",
      "image_path": "https://cdn.sportmonks.com/images/soccer/players/13/37266285.png",
      "age": 23,
      "height": 184,
      "weight": null,
      "nationality": "Germany",
      "position": "DF",
      "position_id": 25,
      "jersey_number": 23,
      "slug": "louis-oppie"
    },
    {
      "id": 155152,
      "display_name": "Adam Dzwigala",
      "image_path": "https://cdn.sportmonks.com/images/soccer/players/16/155152.png",
      "age": 29,
      "height": 185,
      "weight": 80,
      "nationality": "Poland",
      "position": "DF",
      "position_id": 25,
      "jersey_number": 25,
      "slug": "adam-dzwigala"
    },
    {
      "id": 37590019,
      "display_name": "Jannik Robatsch",
      "image_path": "https://cdn.sportmonks.com/images/soccer/players/3/37590019.png",
      "age": 20,
      "height": 190,
      "weight": null,
      "nationality": "Austria",
      "position": "DF",
      "position_id": 25,
      "jersey_number": 34,
      "slug": "jannik-robatsch"
    },
    {
      "id": 1548470,
      "display_name": "James Sands",
      "image_path": "https://cdn.sportmonks.com/images/soccer/players/22/1548470.png",
      "age": 25,
      "height": 186,
      "weight": 73,
      "nationality": "United States",
      "position": "MF",
      "position_id": 26,
      "jersey_number": 6,
      "slug": "james-sands"
    },
    {
      "id": 6605,
      "display_name": "Jackson Irvine ",
      "image_path": "https://cdn.sportmonks.com/images/soccer/players/13/6605.png",
      "age": 32,
      "height": 189,
      "weight": 77,
      "nationality": "Australia",
      "position": "MF",
      "position_id": 26,
      "jersey_number": 7,
      "slug": "jackson-irvine "
    },
    {
      "id": 141099,
      "display_name": "Danel Sinani",
      "image_path": "https://cdn.sportmonks.com/images/soccer/players/11/141099.png",
      "age": 28,
      "height": 185,
      "weight": null,
      "nationality": "Luxembourg",
      "position": "MF",
      "position_id": 26,
      "jersey_number": 10,
      "slug": "danel-sinani"
    },
    {
      "id": 37315722,
      "display_name": "Joel Chima Fujita",
      "image_path": "https://cdn.sportmonks.com/images/soccer/players/10/37315722.png",
      "age": 23,
      "height": 175,
      "weight": 72,
      "nationality": "Japan",
      "position": "MF",
      "position_id": 26,
      "jersey_number": 16,
      "slug": "joel-chima-fujita"
    },
    {
      "id": 28165498,
      "display_name": "Erik Ahlstrand",
      "image_path": "https://cdn.sportmonks.com/images/soccer/players/26/28165498.png",
      "age": 23,
      "height": 184,
      "weight": null,
      "nationality": "Sweden",
      "position": "MF",
      "position_id": 26,
      "jersey_number": 20,
      "slug": "erik-ahlstrand"
    },
    {
      "id": 3526183,
      "display_name": "Connor Metcalfe",
      "image_path": "https://cdn.sportmonks.com/images/soccer/players/7/3526183.png",
      "age": 25,
      "height": 183,
      "weight": 70,
      "nationality": "Australia",
      "position": "MF",
      "position_id": 26,
      "jersey_number": 24,
      "slug": "connor-metcalfe"
    },
    {
      "id": 37676401,
      "display_name": "Marwin Schmitz",
      "image_path": "https://cdn.sportmonks.com/images/soccer/players/17/37676401.png",
      "age": 18,
      "height": 180,
      "weight": null,
      "nationality": "Germany",
      "position": "MF",
      "position_id": 26,
      "jersey_number": 42,
      "slug": "marwin-schmitz"
    },
    {
      "id": 37761046,
      "display_name": "Abdoulie Ceesay",
      "image_path": "https://cdn.sportmonks.com/images/soccer/players/22/37761046.png",
      "age": 21,
      "height": 185,
      "weight": null,
      "nationality": "Gambia",
      "position": "FW",
      "position_id": 27,
      "jersey_number": 9,
      "slug": "abdoulie-ceesay"
    },
    {
      "id": 18683,
      "display_name": "Oladapo Afolayan",
      "image_path": "https://cdn.sportmonks.com/images/soccer/players/27/18683.png",
      "age": 27,
      "height": 180,
      "weight": 73,
      "nationality": "England",
      "position": "FW",
      "position_id": 27,
      "jersey_number": 17,
      "slug": "oladapo-afolayan"
    },
    {
      "id": 21763134,
      "display_name": "Scott Banks",
      "image_path": "https://cdn.sportmonks.com/images/soccer/players/30/21763134.png",
      "age": 23,
      "height": 183,
      "weight": null,
      "nationality": "Scotland",
      "position": "FW",
      "position_id": 27,
      "jersey_number": 18,
      "slug": "scott-banks"
    },
    {
      "id": 37304039,
      "display_name": "Ricky-Jade Jones",
      "image_path": "https://cdn.sportmonks.com/images/soccer/players/7/37304039.png",
      "age": 22,
      "height": 183,
      "weight": null,
      "nationality": "England",
      "position": "FW",
      "position_id": 27,
      "jersey_number": 26,
      "slug": "ricky-jade-jones"
    },
    {
      "id": 37291444,
      "display_name": "Andréas Hountondji",
      "image_path": "https://cdn.sportmonks.com/images/soccer/players/20/37291444.png",
      "age": 23,
      "height": 190,
      "weight": null,
      "nationality": "France",
      "position": "FW",
      "position_id": 27,
      "jersey_number": 27,
      "slug": "andréas-hountondji"
    },
    {
      "id": 99117,
      "display_name": "Mathias Pereira Lage",
      "image_path": "https://cdn.sportmonks.com/images/soccer/players/13/99117.png",
      "age": 28,
      "height": 180,
      "weight": 67,
      "nationality": "Portugal",
      "position": "FW",
      "position_id": 27,
      "jersey_number": 28,
      "slug": "mathias-pereira-lage"
    },
    {
      "id": 37596230,
      "display_name": "Romeo Aigbekaen",
      "image_path": "https://cdn.sportmonks.com/images/soccer/players/6/37596230.png",
      "age": 21,
      "height": 189,
      "weight": null,
      "nationality": "Germany",
      "position": "FW",
      "position_id": 27,
      "jersey_number": 38,
      "slug": "romeo-aigbekaen"
    }
  ]
}